flexisettings/__init__.py
flexisettings/settings.py
django_flexisettings-0.3.1.dist-info/LICENSE
django_flexisettings-0.3.1.dist-info/METADATA
django_flexisettings-0.3.1.dist-info/WHEEL
django_flexisettings-0.3.1.dist-info/top_level.txt
django_flexisettings-0.3.1.dist-info/RECORD
