Metadata-Version: 2.1
Name: django-flexisettings
Version: 0.3.1
Summary: Django flexible settings with running environment support, separate security files and project layout detection.
Home-page: https://github.com/ledapei/django-flexisettings
Author: LeDaPei
Author-email: code@ledapei.com
License: 3-clause BSD licence, see LICENCE.txt
Platform: UNKNOWN
Classifier: Environment :: Web Environment
Classifier: Framework :: Django
Classifier: Intended Audience :: Developers
Classifier: License :: OSI Approved :: BSD License
Classifier: Operating System :: OS Independent
Classifier: Programming Language :: Python
Classifier: Programming Language :: Python :: 2.6
Classifier: Topic :: Internet :: WWW/HTTP
Classifier: Topic :: Internet :: WWW/HTTP :: Dynamic Content
